[{"name":"render_template.action_view","payload":{"identifier":"/Users/liamdarmody/Projects/wdi/projects/thepledge/app/views/pages/home.haml","layout":"layouts/application"},"time":"2015-02-09T19:57:27.013+11:00","transaction_id":"45f7670304a7c0d480b5","end":"2015-02-09T19:57:27.014+11:00","children":[],"duration":0.778},{"name":"process_action.action_controller","payload":{"controller":"PagesController","action":"home","params":{"controller":"pages","action":"home"},"format":"html","method":"GET","path":"/","status":200,"view_runtime":159.243,"db_runtime":0},"time":"2015-02-09T19:57:27.009+11:00","transaction_id":"45f7670304a7c0d480b5","end":"2015-02-09T19:57:27.169+11:00","children":[],"duration":159.941}]