[{"name":"sql.active_record","payload":{"sql":"SELECT  \"users\".* FROM \"users\" WHERE \"users\".\"id\" = $1 LIMIT 1","name":"User Load","connection_id":70313239415420,"statement_name":"a1","binds":[[{"array":false,"name":"id","cast_type":{"precision":null,"scale":null,"limit":null,"range":"-2147483648...2147483648"},"sql_type":"integer","null":false,"default":null,"default_function":"nextval('users_id_seq'::regclass)"},19]],"line":11,"filename":"/Users/liamdarmody/Projects/wdi/projects/thepledge/app/controllers/application_controller.rb","method":"authenticate"},"time":"2015-02-09T14:31:17.801+11:00","transaction_id":"8e6ba8ed4c7f1528d733","end":"2015-02-09T14:31:17.802+11:00","children":[],"duration":0.954},{"name":"sql.active_record","payload":{"sql":"BEGIN","name":null,"connection_id":70313239415420,"statement_name":null,"binds":[],"line":14,"filename":"/Users/liamdarmody/Projects/wdi/projects/thepledge/app/controllers/challenges_controller.rb","method":"create"},"time":"2015-02-09T14:31:17.809+11:00","transaction_id":"8e6ba8ed4c7f1528d733","end":"2015-02-09T14:31:17.810+11:00","children":[],"duration":0.8180000000000001},{"name":"sql.active_record","payload":{"sql":"INSERT INTO \"challenges\" (\"title\", \"description\", \"nominee_name\", \"nominee_email\", \"banner_image\", \"cause\", \"target\", \"created_at\", \"updated_at\") VALUES ($1, $2, $3, $4, $5, $6, $7, $8, $9) RETURNING \"id\"","name":"SQL","connection_id":70313239415420,"statement_name":"a4","binds":[[{"array":false,"name":"title","cast_type":{"precision":null,"scale":null,"limit":null},"sql_type":"character varying","null":true,"default":null,"default_function":null},"Test Association"],[{"array":false,"name":"description","cast_type":{"precision":null,"scale":null,"limit":null},"sql_type":"character varying","null":true,"default":null,"default_function":null},"dsfs"],[{"array":false,"name":"nominee_name","cast_type":{"precision":null,"scale":null,"limit":null},"sql_type":"character varying","null":true,"default":null,"default_function":null},"sdfsd"],[{"array":false,"name":"nominee_email","cast_type":{"precision":null,"scale":null,"limit":null},"sql_type":"character varying","null":true,"default":null,"default_function":null},"sdfsdf"],[{"array":false,"name":"banner_image","cast_type":{"precision":null,"scale":null,"limit":null},"sql_type":"text","null":true,"default":null,"default_function":null},""],[{"array":false,"name":"cause","cast_type":{"precision":null,"scale":null,"limit":null},"sql_type":"character varying","null":true,"default":null,"default_function":null},"sdfds"],[{"array":false,"name":"target","cast_type":{"precision":null,"scale":null,"limit":null},"sql_type":"character varying","null":true,"default":null,"default_function":null},"$200"],[{"array":false,"name":"created_at","cast_type":{"precision":null,"scale":null,"limit":null},"sql_type":"timestamp without time zone","null":true,"default":null,"default_function":null},"2015-02-09 03:31:17.812838"],[{"array":false,"name":"updated_at","cast_type":{"precision":null,"scale":null,"limit":null},"sql_type":"timestamp without time zone","null":true,"default":null,"default_function":null},"2015-02-09 03:31:17.812838"]],"line":14,"filename":"/Users/liamdarmody/Projects/wdi/projects/thepledge/app/controllers/challenges_controller.rb","method":"create"},"time":"2015-02-09T14:31:17.814+11:00","transaction_id":"8e6ba8ed4c7f1528d733","end":"2015-02-09T14:31:17.815+11:00","children":[],"duration":1.377},{"name":"sql.active_record","payload":{"sql":"COMMIT","name":null,"connection_id":70313239415420,"statement_name":null,"binds":[],"line":14,"filename":"/Users/liamdarmody/Projects/wdi/projects/thepledge/app/controllers/challenges_controller.rb","method":"create"},"time":"2015-02-09T14:31:17.821+11:00","transaction_id":"8e6ba8ed4c7f1528d733","end":"2015-02-09T14:31:17.941+11:00","children":[],"duration":120.599},{"name":"sql.active_record","payload":{"sql":"BEGIN","name":null,"connection_id":70313239415420,"statement_name":null,"binds":[],"line":15,"filename":"/Users/liamdarmody/Projects/wdi/projects/thepledge/app/controllers/challenges_controller.rb","method":"create"},"time":"2015-02-09T14:31:17.954+11:00","transaction_id":"8e6ba8ed4c7f1528d733","end":"2015-02-09T14:31:17.957+11:00","children":[],"duration":2.493},{"name":"sql.active_record","payload":{"sql":"UPDATE \"challenges\" SET \"user_id\" = $1, \"updated_at\" = $2 WHERE \"challenges\".\"id\" = $3","name":"SQL","connection_id":70313239415420,"statement_name":"a5","binds":[[{"array":false,"name":"user_id","cast_type":{"precision":null,"scale":null,"limit":null,"range":"-2147483648...2147483648"},"sql_type":"integer","null":true,"default":null,"default_function":null},19],[{"array":false,"name":"updated_at","cast_type":{"precision":null,"scale":null,"limit":null},"sql_type":"timestamp without time zone","null":true,"default":null,"default_function":null},"2015-02-09 03:31:17.961984"],[{"array":false,"name":"id","cast_type":{"precision":null,"scale":null,"limit":null,"range":"-2147483648...2147483648"},"sql_type":"integer","null":false,"default":null,"default_function":"nextval('challenges_id_seq'::regclass)"},10]],"line":15,"filename":"/Users/liamdarmody/Projects/wdi/projects/thepledge/app/controllers/challenges_controller.rb","method":"create"},"time":"2015-02-09T14:31:17.963+11:00","transaction_id":"8e6ba8ed4c7f1528d733","end":"2015-02-09T14:31:17.965+11:00","children":[],"duration":1.067},{"name":"sql.active_record","payload":{"sql":"COMMIT","name":null,"connection_id":70313239415420,"statement_name":null,"binds":[],"line":15,"filename":"/Users/liamdarmody/Projects/wdi/projects/thepledge/app/controllers/challenges_controller.rb","method":"create"},"time":"2015-02-09T14:31:17.969+11:00","transaction_id":"8e6ba8ed4c7f1528d733","end":"2015-02-09T14:31:17.984+11:00","children":[],"duration":14.821000000000002},{"name":"process_action.action_controller","payload":{"controller":"ChallengesController","action":"create","params":{"utf8":"✓","authenticity_token":"yA2i1LMrz6mFl/TvKFmb4bRNtyZqrxIiV79SbZHPSy+T1HHb+ENJIo1epUsPfBPsDc4cLx4PVjcuDQjDmGT8nQ==","challenge":{"title":"Test Association","description":"dsfs","nominee_name":"sdfsd","nominee_email":"sdfsdf","banner_image":"","cause":"sdfds","target":"$200"},"commit":"Create Challenge","controller":"challenges","action":"create"},"format":"html","method":"POST","path":"/challenges","status":302,"view_runtime":null,"db_runtime":134.387},"time":"2015-02-09T14:31:17.800+11:00","transaction_id":"e45c891a589de0febc01","end":"2015-02-09T14:31:17.988+11:00","children":[],"duration":188.184}]