[{"name":"sql.active_record","payload":{"sql":"SELECT \"challenges\".* FROM \"challenges\"","name":"Challenge Load","connection_id":70270126281300,"statement_name":null,"binds":[],"line":3,"filename":"/Users/liamdarmody/Projects/wdi/projects/thepledge/app/views/challenges/index.html.erb","method":"_app_views_challenges_index_html_erb___3687780300126908013_70270150820140"},"time":"2015-02-08T22:11:12.096+11:00","transaction_id":"61ee78d335e3584f4e21","end":"2015-02-08T22:11:12.099+11:00","children":[],"duration":3.559},{"name":"render_template.action_view","payload":{"identifier":"/Users/liamdarmody/Projects/wdi/projects/thepledge/app/views/challenges/index.html.erb","layout":"layouts/application"},"time":"2015-02-08T22:11:12.091+11:00","transaction_id":"00b012cb8c64ada83787","end":"2015-02-08T22:11:12.105+11:00","children":[],"duration":13.868},{"name":"process_action.action_controller","payload":{"controller":"ChallengesController","action":"index","params":{"controller":"challenges","action":"index"},"format":"html","method":"GET","path":"/challenges","status":200,"view_runtime":138.60199999999998,"db_runtime":2.2880000000000003},"time":"2015-02-08T22:11:12.051+11:00","transaction_id":"00b012cb8c64ada83787","end":"2015-02-08T22:11:12.194+11:00","children":[],"duration":142.862}]